README.txt
setup.cfg
setup.py
docs/HISTORY.txt
docs/LICENSE.GPL
docs/LICENSE.txt
docs/MANUAL.txt
raptus/__init__.py
raptus.article.randomcontent.egg-info/PKG-INFO
raptus.article.randomcontent.egg-info/SOURCES.txt
raptus.article.randomcontent.egg-info/dependency_links.txt
raptus.article.randomcontent.egg-info/entry_points.txt
raptus.article.randomcontent.egg-info/namespace_packages.txt
raptus.article.randomcontent.egg-info/not-zip-safe
raptus.article.randomcontent.egg-info/requires.txt
raptus.article.randomcontent.egg-info/top_level.txt
raptus/article/__init__.py
raptus/article/randomcontent/__init__.py
raptus/article/randomcontent/configure.zcml
raptus/article/randomcontent/interfaces.py
raptus/article/randomcontent/randomcontent.py
raptus/article/randomcontent/browser/__init__.py
raptus/article/randomcontent/browser/configure.zcml
raptus/article/randomcontent/browser/randomcontent.pt
raptus/article/randomcontent/browser/randomcontent.py
raptus/article/randomcontent/browser/randomcontent_full.gif
raptus/article/randomcontent/browser/randomcontent_left.gif
raptus/article/randomcontent/browser/randomcontent_right.gif
raptus/article/randomcontent/browser/randomcontent_teaser.gif
raptus/article/randomcontent/i18n/raptus.article-de.po
raptus/article/randomcontent/i18n/raptus.article-fr.po
raptus/article/randomcontent/i18n/raptus.article.pot
raptus/article/randomcontent/profiles/default/metadata.xml
raptus/article/randomcontent/profiles/default/propertiestool.xml
raptus/article/randomcontent/profiles/default/viewlets.xml