Metadata-Version: 1.0
Name: raptus.article.randomcontent
Version: 2.0b5
Summary: Provides a component which displays a random article.
Home-page: http://raptus.com
Author: Raptus AG
Author-email: dev@raptus.com
License: GPL
Platform: UNKNOWN
Classifier: Programming Language :: Python
Classifier: Topic :: Software Development :: Libraries :: Python Modules
